backwork/__init__.py
backwork/backup.py
backwork/backwork.py
backwork/download.py
backwork/notifiers.py
backwork/restore.py
backwork/show.py
backwork/upload.py
backwork/lib/__init__.py
backwork/lib/utils.py
backwork-0.3.1.dist-info/LICENSE
backwork-0.3.1.dist-info/METADATA
backwork-0.3.1.dist-info/WHEEL
backwork-0.3.1.dist-info/entry_points.txt
backwork-0.3.1.dist-info/top_level.txt
backwork-0.3.1.dist-info/RECORD
